<?xml version="1.0" encoding="utf-8"?>
<TextureAtlas imagePath="gfDanceTitle.png">
	<!-- Created with Adobe Animate version 18.0.1.115 -->
	<!-- http://www.adobe.com/products/animate.html -->
	<SubTexture name="gfDance0000" x="10" y="10" width="724" height="648"/>
	<SubTexture name="gfDance0001" x="744" y="10" width="724" height="648"/>
	<SubTexture name="gfDance0002" x="1478" y="10" width="724" height="648"/>
	<SubTexture name="gfDance0003" x="2212" y="10" width="724" height="648"/>
	<SubTexture name="gfDance0004" x="2946" y="10" width="724" height="648"/>
	<SubTexture name="gfDance0005" x="10" y="668" width="724" height="648"/>
	<SubTexture name="gfDance0006" x="744" y="668" width="724" height="648"/>
	<SubTexture name="gfDance0007" x="1478" y="668" width="724" height="648"/>
	<SubTexture name="gfDance0008" x="1478" y="668" width="724" height="648"/>
	<SubTexture name="gfDance0009" x="1478" y="668" width="724" height="648"/>
	<SubTexture name="gfDance0010" x="2212" y="668" width="724" height="648"/>
	<SubTexture name="gfDance0011" x="2212" y="668" width="724" height="648"/>
	<SubTexture name="gfDance0012" x="2212" y="668" width="724" height="648"/>
	<SubTexture name="gfDance0013" x="2946" y="668" width="724" height="648"/>
	<SubTexture name="gfDance0014" x="2946" y="668" width="724" height="648"/>
	<SubTexture name="gfDance0015" x="10" y="1326" width="724" height="648"/>
	<SubTexture name="gfDance0016" x="744" y="1326" width="724" height="648"/>
	<SubTexture name="gfDance0017" x="1478" y="1326" width="724" height="648"/>
	<SubTexture name="gfDance0018" x="2212" y="1326" width="724" height="648"/>
	<SubTexture name="gfDance0019" x="2946" y="1326" width="724" height="648"/>
	<SubTexture name="gfDance0020" x="10" y="1984" width="724" height="648"/>
	<SubTexture name="gfDance0021" x="744" y="1984" width="724" height="648"/>
	<SubTexture name="gfDance0022" x="1478" y="1984" width="724" height="648"/>
	<SubTexture name="gfDance0023" x="1478" y="1984" width="724" height="648"/>
	<SubTexture name="gfDance0024" x="1478" y="1984" width="724" height="648"/>
	<SubTexture name="gfDance0025" x="2212" y="1984" width="724" height="648"/>
	<SubTexture name="gfDance0026" x="2212" y="1984" width="724" height="648"/>
	<SubTexture name="gfDance0027" x="2212" y="1984" width="724" height="648"/>
	<SubTexture name="gfDance0028" x="2946" y="1984" width="724" height="648"/>
	<SubTexture name="gfDance0029" x="2946" y="1984" width="724" height="648"/>
</TextureAtlas>
